nonebot_plugin_duel/__init__.py
nonebot_plugin_duel/config.py
nonebot_plugin_duel/dule_sesion.py
nonebot_plugin_duel/matcher.py
nonebot_plugin_duel/rule.py
nonebot_plugin_duel-0.1.2.dist-info/LICENSE
nonebot_plugin_duel-0.1.2.dist-info/METADATA
nonebot_plugin_duel-0.1.2.dist-info/WHEEL
nonebot_plugin_duel-0.1.2.dist-info/top_level.txt
nonebot_plugin_duel-0.1.2.dist-info/RECORD
