Metadata-Version: 2.1
Name: nonebot_plugin_duel
Version: 0.1.2
Summary: nonebot-plugin-duel
Home-page: https://github.com/Redmomn/nonebot-plugin-duel
Author: Redmomn
Author-email: 109732988+Redmomn@users.noreply.github.com
License: MIT
Keywords: nonebot2,duel
License-File: LICENSE
Requires-Dist: nonebot-adapter-onebot >=2.0.0
Requires-Dist: nonebot2 >=2.0.0
